_tagpy.cpython-314-x86_64-linux-gnu.so
tagpy/__init__.py
tagpy/ape.py
tagpy/flac.py
tagpy/id3v1.py
tagpy/id3v2.py
tagpy/mp4.py
tagpy/mpc.py
tagpy/mpeg.py
tagpy/wav.py
tagpy/ogg/__init__.py
tagpy/ogg/flac.py
tagpy/ogg/opus.py
tagpy/ogg/vorbis.py
tagpy.libs/libboost_python314-mt-x64-8a289367.so.1.89.0
tagpy.libs/libtag-b360f7a1.so.2.0.2
tagpy-2025.1.dist-info/METADATA
tagpy-2025.1.dist-info/WHEEL
tagpy-2025.1.dist-info/top_level.txt
tagpy-2025.1.dist-info/RECORD
tagpy-2025.1.dist-info/licenses/LICENSE
