Metadata-Version: 2.4
Name: tagpy
Version: 2025.1
Summary: Python Bindings for TagLib
Home-page: https://github.com/palfrey/tagpy
Author: Tom Parker-Shemilt
Author-email: palfrey@tevp.net
License: MIT
Classifier: Development Status :: 5 - Production/Stable
Classifier: Intended Audience :: Developers
Classifier: License :: OSI Approved :: MIT License
Classifier: Natural Language :: English
Classifier: Operating System :: OS Independent
Classifier: Operating System :: POSIX
Classifier: Operating System :: Unix
Classifier: Programming Language :: Python
Classifier: Programming Language :: Python :: 3
Classifier: Topic :: Multimedia :: Sound/Audio
Classifier: Topic :: Multimedia :: Sound/Audio :: CD Audio :: CD Ripping
Classifier: Topic :: Multimedia :: Sound/Audio :: Editors
Classifier: Topic :: Software Development :: Libraries :: Python Modules
Classifier: Topic :: Utilities
Requires-Python: >=3.10, <4
License-File: LICENSE
Requires-Dist: packaging>=14.0
Dynamic: author
Dynamic: author-email
Dynamic: classifier
Dynamic: description
Dynamic: description-content-type
Dynamic: home-page
Dynamic: license
Dynamic: license-file
Dynamic: requires-dist
Dynamic: requires-python
Dynamic: summary
